spotifywebapipython/__init__.py
spotifywebapipython/const.py
spotifywebapipython/saappmessages.py
spotifywebapipython/sautils.py
spotifywebapipython/spotifyapierror.py
spotifywebapipython/spotifyapimessage.py
spotifywebapipython/spotifyauthtoken.py
spotifywebapipython/spotifyclient.py
spotifywebapipython/spotifydiscovery.py
spotifywebapipython/spotifymediatypes.py
spotifywebapipython/spotifywebapiauthenticationerror.py
spotifywebapipython/spotifywebapierror.py
spotifywebapipython/spotifywebplayertoken.py
spotifywebapipython/docs/__init__.html
spotifywebapipython/docs/codecopy.js
spotifywebapipython/docs/index.html
spotifywebapipython/docs/search.js
spotifywebapipython/docs/spotifywebapipython.ico
spotifywebapipython/docs/spotifywebapipython_OLD.ico
spotifywebapipython/docs/spotifywebapipython/const.html
spotifywebapipython/docs/spotifywebapipython/saappmessages.html
spotifywebapipython/docs/spotifywebapipython/sautils.html
spotifywebapipython/docs/spotifywebapipython/spotifyapierror.html
spotifywebapipython/docs/spotifywebapipython/spotifyapimessage.html
spotifywebapipython/docs/spotifywebapipython/spotifyauthtoken.html
spotifywebapipython/docs/spotifywebapipython/spotifyclient.html
spotifywebapipython/docs/spotifywebapipython/spotifydiscovery.html
spotifywebapipython/docs/spotifywebapipython/spotifywebapiauthenticationerror.html
spotifywebapipython/docs/spotifywebapipython/spotifywebapierror.html
spotifywebapipython/docs/spotifywebapipython/spotifywebplayertoken.html
spotifywebapipython/models/__init__.py
spotifywebapipython/models/album.py
spotifywebapipython/models/albumpagesaved.py
spotifywebapipython/models/albumpagesimplified.py
spotifywebapipython/models/albumsaved.py
spotifywebapipython/models/albumsimplified.py
spotifywebapipython/models/artist.py
spotifywebapipython/models/artistinfo.py
spotifywebapipython/models/artistinfotourevent.py
spotifywebapipython/models/artistpage.py
spotifywebapipython/models/artistsimplified.py
spotifywebapipython-1.0.259.dist-info/LICENSE
spotifywebapipython-1.0.259.dist-info/METADATA
spotifywebapipython-1.0.259.dist-info/WHEEL
spotifywebapipython-1.0.259.dist-info/top_level.txt
spotifywebapipython-1.0.259.dist-info/RECORD
