Metadata-Version: 2.1
Name: spotifywebapipython
Version: 1.0.259
Summary: Spotify Web API Python3 Library
Author: Todd Lucas
Author-email: <thlucas@yahoo.com>
Project-URL: Changelog, https://github.com/thlucas1/spotifywebapiPython/blob/master/CHANGELOG.md
Project-URL: Documentation, https://spotifywebapiPython.readthedocs.io/en/latest/__init__.html
Project-URL: GitHub, https://github.com/thlucas1/spotifywebapiPython
Keywords: spotify,spotifywebapi,api,audio,music,library
Classifier: Development Status :: 5 - Production/Stable
Classifier: Intended Audience :: Developers
Classifier: Programming Language :: Python :: 3
Classifier: Operating System :: Microsoft :: Windows
Classifier: Operating System :: MacOS :: MacOS X
Classifier: Operating System :: Unix
Classifier: Topic :: Software Development :: Libraries
Classifier: Topic :: Multimedia :: Sound/Audio :: Players
Classifier: Natural Language :: English
Classifier: License :: OSI Approved :: MIT License
Requires-Python: >=3.11.0
License-File: LICENSE
Requires-Dist: lxml >=5.2.0
Requires-Dist: numpy >=2.3.2
Requires-Dist: oauthlib >=3.2.2
Requires-Dist: pillow >=11.3.0
Requires-Dist: platformdirs >=4.1.0
Requires-Dist: PyChromecast >=14.0.7
Requires-Dist: pyotp >=2.9.0
Requires-Dist: requests >=2.31.0
Requires-Dist: requests-oauthlib >=1.3.1
Requires-Dist: smartinspectpython >=3.0.38
Requires-Dist: soco >=0.30.6
Requires-Dist: urllib3 >=2.0
Requires-Dist: zeroconf >=0.132.2
